airouter/__init__.py
airouter/models.py
airouter/providers/__init__.py
airouter/providers/aws_bedrock_chat_provider.py
airouter/providers/aws_bedrock_provider.py
airouter/providers/azure_openai_provider.py
airouter/providers/base_provider.py
airouter/providers/factory.py
airouter/providers/ollama_provider.py
airouter/providers/openai_provider.py
airouter/providers/vertex_ai_text_provider.py
airouter/streamed_completion.py
airouter/utils/__init__.py
airouter/utils/interactive.py
airouter/utils/logs.py
airouter/utils/tokens.py
airouter/xperiments/exp_multi.py
airouter/xperiments/exp_simple.py
airouter/xperiments/exp_vision.py
airouter-0.1.45.dist-info/LICENSE
airouter-0.1.45.dist-info/METADATA
airouter-0.1.45.dist-info/WHEEL
airouter-0.1.45.dist-info/RECORD
