Metadata-Version: 2.1
Name: airouter
Version: 0.1.45
Summary: 
Author: Laurentiu Piciu
Author-email: laurentiupiciu@gmail.com
Requires-Python: >=3.10
Classifier: Programming Language :: Python :: 3
Classifier: Programming Language :: Python :: 3.10
Classifier: Programming Language :: Python :: 3.11
Classifier: Programming Language :: Python :: 3.12
Requires-Dist: httpx (>=0.25.0)
Requires-Dist: pydantic (>=2.4.2)
Requires-Dist: python-decouple (>=3.8)
Requires-Dist: requests (>=2.31.0)
Requires-Dist: tenacity (>=8.0)
Requires-Dist: tiktoken (>=0.7.0)
